aws_pcluster_bootstrap_helpers/__init__.py
aws_pcluster_bootstrap_helpers/_version.py
aws_pcluster_bootstrap_helpers/cli.py
aws_pcluster_bootstrap_helpers/commands/__init__.py
aws_pcluster_bootstrap_helpers/commands/cli_build_ami.py
aws_pcluster_bootstrap_helpers/commands/cli_configure.py
aws_pcluster_bootstrap_helpers/commands/cli_create_cluster.py
aws_pcluster_bootstrap_helpers/commands/cli_instance_types.py
aws_pcluster_bootstrap_helpers/commands/cli_upgrade.py
aws_pcluster_bootstrap_helpers/models/__init__.py
aws_pcluster_bootstrap_helpers/models/terraform_models.py
aws_pcluster_bootstrap_helpers/utils/__init__.py
aws_pcluster_bootstrap_helpers/utils/cloudwatch.py
aws_pcluster_bootstrap_helpers/utils/commands.py
aws_pcluster_bootstrap_helpers/utils/constants.py
aws_pcluster_bootstrap_helpers/utils/dns.py
aws_pcluster_bootstrap_helpers/utils/efs.py
aws_pcluster_bootstrap_helpers/utils/logging.py
aws_pcluster_bootstrap_helpers/utils/network.py
aws_pcluster_bootstrap_helpers/utils/pcluster_version.py
aws_pcluster_bootstrap_helpers-3.26.0.dist-info/LICENSE
aws_pcluster_bootstrap_helpers-3.26.0.dist-info/METADATA
aws_pcluster_bootstrap_helpers-3.26.0.dist-info/WHEEL
aws_pcluster_bootstrap_helpers-3.26.0.dist-info/entry_points.txt
aws_pcluster_bootstrap_helpers-3.26.0.dist-info/top_level.txt
aws_pcluster_bootstrap_helpers-3.26.0.dist-info/RECORD
