Metadata-Version: 2.1
Name: aws-pcluster-bootstrap-helpers
Version: 3.26.0
Summary: Helpers to bootstrap a AWS PCluster + SLURM + Custom AMIs
Home-page: https://github.com/dabble-of-devops-bioanalyze/aws_pcluster_bootstrap_helpers
Author: Jillian Rowe
Author-email: jillian@dabbleofdevops.com
License: Apache Software License 2.0
Keywords: aws_pcluster_bootstrap_helpers
Classifier: Development Status :: 2 - Pre-Alpha
Classifier: Intended Audience :: Developers
Classifier: License :: OSI Approved :: Apache Software License
Classifier: Natural Language :: English
Classifier: Programming Language :: Python :: 3
Classifier: Programming Language :: Python :: 3.6
Classifier: Programming Language :: Python :: 3.7
Classifier: Programming Language :: Python :: 3.8
Requires-Python: >=3.6
License-File: LICENSE
Requires-Dist: typer
Requires-Dist: typer[all]
Requires-Dist: rich
Requires-Dist: inquirer
Requires-Dist: colorlog
Requires-Dist: textual
Requires-Dist: datasize
Requires-Dist: questionary
Requires-Dist: boto3-stubs[batch,ec2,essential,logs,s3]
Requires-Dist: boto3
Requires-Dist: funcy
Requires-Dist: humanize
Requires-Dist: cookiecutter
Requires-Dist: pandas
Requires-Dist: numpy
